{"cameraMode":{"drawMode":0,"name":"Shaded","section":"Shading Mode"},"sceneLighting":true,"audioPlay":false,"sceneViewState":{"showFog":true,"showMaterialUpdate":false,"showSkybox":true,"showFlares":true,"showImageEffects":true,"showParticleSystems":true},"in2DMode":false,"pivot":{"x":-70.68513488769531,"y":-41.955650329589847,"z":-24.67892837524414},"rotation":{"x":-0.07419625669717789,"y":0.8348350524902344,"z":-0.11620286852121353,"w":-0.5329819321632385},"size":89.20337677001953,"orthographic":false}